dartmouth_auth/__init__.py
dartmouth_auth/definitions.py
dartmouth_auth/jwt.py
dartmouth_auth-0.0.4.dist-info/METADATA
dartmouth_auth-0.0.4.dist-info/WHEEL
dartmouth_auth-0.0.4.dist-info/licenses/LICENSE
dartmouth_auth-0.0.4.dist-info/RECORD
