Metadata-Version: 2.4
Name: dartmouth_auth
Version: 0.0.4
Summary: A lightweight package facilitating authentication for Dartmouth services.
Project-URL: Homepage, https://github.com/dartmouth/dartmouth-auth
Project-URL: Issues, https://github.com/dartmouth/dartmouth-auth/issues
Author-email: Simon Stone <simon.stone@dartmouth.edu>
License-File: LICENSE
Classifier: License :: OSI Approved :: MIT License
Classifier: Operating System :: OS Independent
Classifier: Programming Language :: Python :: 3
Requires-Python: >=3.8
Requires-Dist: requests
